{
  "date" : "2026-03-02",
  "百度热搜" : [ {
    "title" : " 为民造福是最大政绩 ",
    "link" : "https://www.baidu.com/s?wd=%E4%B8%BA%E6%B0%91%E9%80%A0%E7%A6%8F%E6%98%AF%E6%9C%80%E5%A4%A7%E6%94%BF%E7%BB%A9&sa=fyb_news&rsv_dl=fyb_news"
  }, {
    "title" : " 霍尔木兹海峡密密麻麻船只集体趴窝 ",
    "link" : "https://www.baidu.com/s?wd=%E9%9C%8D%E5%B0%94%E6%9C%A8%E5%85%B9%E6%B5%B7%E5%B3%A1%E5%AF%86%E5%AF%86%E9%BA%BB%E9%BA%BB%E8%88%B9%E5%8F%AA%E9%9B%86%E4%BD%93%E8%B6%B4%E7%AA%9D&sa=fyb_news&rsv_dl=fyb_news"
  }, {
    "title" : " 黎巴嫩向以色列发射6枚火箭弹 ",
    "link" : "https://www.baidu.com/s?wd=%E9%BB%8E%E5%B7%B4%E5%AB%A9%E5%90%91%E4%BB%A5%E8%89%B2%E5%88%97%E5%8F%91%E5%B0%846%E6%9E%9A%E7%81%AB%E7%AE%AD%E5%BC%B9&sa=fyb_news&rsv_dl=fyb_news"
  }, {
    "title" : " “超短学期”来了 最新提醒 ",
    "link" : "https://www.baidu.com/s?wd=%E2%80%9C%E8%B6%85%E7%9F%AD%E5%AD%A6%E6%9C%9F%E2%80%9D%E6%9D%A5%E4%BA%86+%E6%9C%80%E6%96%B0%E6%8F%90%E9%86%92&sa=fyb_news&rsv_dl=fyb_news"
  }, {
    "title" : " 中国造全球首款机器人手机亮相 ",
    "link" : "https://www.baidu.com/s?wd=%E4%B8%AD%E5%9B%BD%E9%80%A0%E5%85%A8%E7%90%83%E9%A6%96%E6%AC%BE%E6%9C%BA%E5%99%A8%E4%BA%BA%E6%89%8B%E6%9C%BA%E4%BA%AE%E7%9B%B8&sa=fyb_news&rsv_dl=fyb_news"
  }, {
    "title" : " 99年义乌老板娘谈营业额喜笑颜开 ",
    "link" : "https://www.baidu.com/s?wd=99%E5%B9%B4%E4%B9%89%E4%B9%8C%E8%80%81%E6%9D%BF%E5%A8%98%E8%B0%88%E8%90%A5%E4%B8%9A%E9%A2%9D%E5%96%9C%E7%AC%91%E9%A2%9C%E5%BC%80&sa=fyb_news&rsv_dl=fyb_news"
  }, {
    "title" : " 伊朗外长：伊朗军事能力无任何改变 ",
    "link" : "https://www.baidu.com/s?wd=%E4%BC%8A%E6%9C%97%E5%A4%96%E9%95%BF%EF%BC%9A%E4%BC%8A%E6%9C%97%E5%86%9B%E4%BA%8B%E8%83%BD%E5%8A%9B%E6%97%A0%E4%BB%BB%E4%BD%95%E6%94%B9%E5%8F%98&sa=fyb_news&rsv_dl=fyb_news"
  }, {
    "title" : " 中国军号：对风浪说拜拜对安宁说嗨嗨 ",
    "link" : "https://www.baidu.com/s?wd=%E4%B8%AD%E5%9B%BD%E5%86%9B%E5%8F%B7%EF%BC%9A%E5%AF%B9%E9%A3%8E%E6%B5%AA%E8%AF%B4%E6%8B%9C%E6%8B%9C%E5%AF%B9%E5%AE%89%E5%AE%81%E8%AF%B4%E5%97%A8%E5%97%A8&sa=fyb_news&rsv_dl=fyb_news"
  }, {
    "title" : " “宁古塔”从苦寒之地变冰雪新天地 ",
    "link" : "https://www.baidu.com/s?wd=%E2%80%9C%E5%AE%81%E5%8F%A4%E5%A1%94%E2%80%9D%E4%BB%8E%E8%8B%A6%E5%AF%92%E4%B9%8B%E5%9C%B0%E5%8F%98%E5%86%B0%E9%9B%AA%E6%96%B0%E5%A4%A9%E5%9C%B0&sa=fyb_news&rsv_dl=fyb_news"
  }, {
    "title" : " 有电影院开始尝试：看到烂片可退钱 ",
    "link" : "https://www.baidu.com/s?wd=%E6%9C%89%E7%94%B5%E5%BD%B1%E9%99%A2%E5%BC%80%E5%A7%8B%E5%B0%9D%E8%AF%95%EF%BC%9A%E7%9C%8B%E5%88%B0%E7%83%82%E7%89%87%E5%8F%AF%E9%80%80%E9%92%B1&sa=fyb_news&rsv_dl=fyb_news"
  } ],
  "新浪微博热搜" : [ {
    "title" : "以军超100架战机空袭伊朗",
    "link" : "https://s.weibo.com/weibo?q=%23%E4%BB%A5%E5%86%9B%E8%B6%85100%E6%9E%B6%E6%88%98%E6%9C%BA%E7%A9%BA%E8%A2%AD%E4%BC%8A%E6%9C%97%23&t=31&band_rank=1&Refer=top"
  }, {
    "title" : "演员逼真到根本看不出来是AI",
    "link" : "https://s.weibo.com/weibo?q=%E6%BC%94%E5%91%98%E9%80%BC%E7%9C%9F%E5%88%B0%E6%A0%B9%E6%9C%AC%E7%9C%8B%E4%B8%8D%E5%87%BA%E6%9D%A5%E6%98%AFAI&t=31&band_rank=2&Refer=top"
  }, {
    "title" : "骏马闹元宵贺卡",
    "link" : "https://s.weibo.com/weibo?q=%23%E9%AA%8F%E9%A9%AC%E9%97%B9%E5%85%83%E5%AE%B5%E8%B4%BA%E5%8D%A1%23&t=31&band_rank=3&Refer=top"
  }, {
    "title" : "油价金价大涨",
    "link" : "https://s.weibo.com/weibo?q=%23%E6%B2%B9%E4%BB%B7%E9%87%91%E4%BB%B7%E5%A4%A7%E6%B6%A8%23&t=31&band_rank=4&Refer=top"
  }, {
    "title" : "椰子水",
    "link" : "https://s.weibo.com/weibo?q=%E6%A4%B0%E5%AD%90%E6%B0%B4&t=31&band_rank=5&Refer=top"
  }, {
    "title" : "难怪周杰伦再也没来成都开过演唱会",
    "link" : "https://s.weibo.com/weibo?q=%23%E9%9A%BE%E6%80%AA%E5%91%A8%E6%9D%B0%E4%BC%A6%E5%86%8D%E4%B9%9F%E6%B2%A1%E6%9D%A5%E6%88%90%E9%83%BD%E5%BC%80%E8%BF%87%E6%BC%94%E5%94%B1%E4%BC%9A%23&t=31&band_rank=6&Refer=top"
  }, {
    "title" : "油价",
    "link" : "https://s.weibo.com/weibo?q=%E6%B2%B9%E4%BB%B7&t=31&band_rank=7&Refer=top"
  }, {
    "title" : "小伙腹痛CT查出肠道卡2把勺子",
    "link" : "https://s.weibo.com/weibo?q=%23%E5%B0%8F%E4%BC%99%E8%85%B9%E7%97%9BCT%E6%9F%A5%E5%87%BA%E8%82%A0%E9%81%93%E5%8D%A12%E6%8A%8A%E5%8B%BA%E5%AD%90%23&t=31&band_rank=8&Refer=top"
  }, {
    "title" : "霸王茶姬口令",
    "link" : "https://s.weibo.com/weibo?q=%E9%9C%B8%E7%8E%8B%E8%8C%B6%E5%A7%AC%E5%8F%A3%E4%BB%A4&t=31&band_rank=9&Refer=top"
  }, {
    "title" : "苏翊鸣北京夺冠后一度空虚",
    "link" : "https://s.weibo.com/weibo?q=%23%E8%8B%8F%E7%BF%8A%E9%B8%A3%E5%8C%97%E4%BA%AC%E5%A4%BA%E5%86%A0%E5%90%8E%E4%B8%80%E5%BA%A6%E7%A9%BA%E8%99%9A%23&t=31&band_rank=10&Refer=top"
  } ],
  "今日头条热榜" : [ {
    "title" : "伊朗前总统内贾德遇袭身亡",
    "link" : "https://www.toutiao.com/trending/7612280693275643430/?category_name=topic_innerflow&event_type=hot_board&log_pb=%7B%22category_name%22%3A%22topic_innerflow%22%2C%22cluster_type%22%3A%222%22%2C%22enter_from%22%3A%22click_category%22%2C%22entrance_hotspot%22%3A%22outside%22%2C%22event_type%22%3A%22hot_board%22%2C%22hot_board_cluster_id%22%3A%227612280693275643430%22%2C%22hot_board_impr_id%22%3A%222026030210222522875065DDD0B16A9F23%22%2C%22jump_page%22%3A%22hot_board_page%22%2C%22location%22%3A%22news_hot_card%22%2C%22page_location%22%3A%22hot_board_page%22%2C%22source%22%3A%22trending_tab%22%2C%22style_id%22%3A%2240132%22%2C%22title%22%3A%22%E4%BC%8A%E6%9C%97%E5%89%8D%E6%80%BB%E7%BB%9F%E5%86%85%E8%B4%BE%E5%BE%B7%E9%81%87%E8%A2%AD%E8%BA%AB%E4%BA%A1%22%7D&rank=&style_id=40132&topic_id=7612280693275643430"
  }, {
    "title" : "全球首款机器人手机亮相MWC",
    "link" : "https://www.toutiao.com/trending/7611736009055191050/?category_name=topic_innerflow&event_type=hot_board&log_pb=%7B%22category_name%22%3A%22topic_innerflow%22%2C%22cluster_type%22%3A%228%22%2C%22enter_from%22%3A%22click_category%22%2C%22entrance_hotspot%22%3A%22outside%22%2C%22event_type%22%3A%22hot_board%22%2C%22hot_board_cluster_id%22%3A%227611736009055191050%22%2C%22hot_board_impr_id%22%3A%222026030210222522875065DDD0B16A9F23%22%2C%22jump_page%22%3A%22hot_board_page%22%2C%22location%22%3A%22news_hot_card%22%2C%22page_location%22%3A%22hot_board_page%22%2C%22source%22%3A%22trending_tab%22%2C%22style_id%22%3A%2240132%22%2C%22title%22%3A%22%E5%85%A8%E7%90%83%E9%A6%96%E6%AC%BE%E6%9C%BA%E5%99%A8%E4%BA%BA%E6%89%8B%E6%9C%BA%E4%BA%AE%E7%9B%B8MWC%22%7D&rank=&style_id=40132&topic_id=7611736009055191050"
  }, {
    "title" : "全国两会知识帖来了",
    "link" : "https://www.toutiao.com/article/7612221305689817641"
  }, {
    "title" : "丈夫在界碑前为妻子补上求婚仪式",
    "link" : "https://www.toutiao.com/trending/7611722623756451903/?category_name=topic_innerflow&event_type=hot_board&log_pb=%7B%22category_name%22%3A%22topic_innerflow%22%2C%22cluster_type%22%3A%226%22%2C%22enter_from%22%3A%22click_category%22%2C%22entrance_hotspot%22%3A%22outside%22%2C%22event_type%22%3A%22hot_board%22%2C%22hot_board_cluster_id%22%3A%227611722623756451903%22%2C%22hot_board_impr_id%22%3A%222026030210222522875065DDD0B16A9F23%22%2C%22jump_page%22%3A%22hot_board_page%22%2C%22location%22%3A%22news_hot_card%22%2C%22page_location%22%3A%22hot_board_page%22%2C%22source%22%3A%22trending_tab%22%2C%22style_id%22%3A%2240132%22%2C%22title%22%3A%22%E4%B8%88%E5%A4%AB%E5%9C%A8%E7%95%8C%E7%A2%91%E5%89%8D%E4%B8%BA%E5%A6%BB%E5%AD%90%E8%A1%A5%E4%B8%8A%E6%B1%82%E5%A9%9A%E4%BB%AA%E5%BC%8F%22%7D&rank=&style_id=40132&topic_id=7611722623756451903"
  }, {
    "title" : "中国军号：不期待那一天但绝不惧怕",
    "link" : "https://www.toutiao.com/trending/7611483176777236499/?category_name=topic_innerflow&event_type=hot_board&log_pb=%7B%22category_name%22%3A%22topic_innerflow%22%2C%22cluster_type%22%3A%222%22%2C%22enter_from%22%3A%22click_category%22%2C%22entrance_hotspot%22%3A%22outside%22%2C%22event_type%22%3A%22hot_board%22%2C%22hot_board_cluster_id%22%3A%227611483176777236499%22%2C%22hot_board_impr_id%22%3A%222026030210222522875065DDD0B16A9F23%22%2C%22jump_page%22%3A%22hot_board_page%22%2C%22location%22%3A%22news_hot_card%22%2C%22page_location%22%3A%22hot_board_page%22%2C%22source%22%3A%22trending_tab%22%2C%22style_id%22%3A%2240132%22%2C%22title%22%3A%22%E4%B8%AD%E5%9B%BD%E5%86%9B%E5%8F%B7%EF%BC%9A%E4%B8%8D%E6%9C%9F%E5%BE%85%E9%82%A3%E4%B8%80%E5%A4%A9%E4%BD%86%E7%BB%9D%E4%B8%8D%E6%83%A7%E6%80%95%22%7D&rank=&style_id=40132&topic_id=7611483176777236499"
  }, {
    "title" : "伊朗：6名美国中情局官员在阿联酋身亡",
    "link" : "https://www.toutiao.com/trending/7612139587531522057/?category_name=topic_innerflow&event_type=hot_board&log_pb=%7B%22category_name%22%3A%22topic_innerflow%22%2C%22cluster_type%22%3A%222%22%2C%22enter_from%22%3A%22click_category%22%2C%22entrance_hotspot%22%3A%22outside%22%2C%22event_type%22%3A%22hot_board%22%2C%22hot_board_cluster_id%22%3A%227612139587531522057%22%2C%22hot_board_impr_id%22%3A%222026030210222522875065DDD0B16A9F23%22%2C%22jump_page%22%3A%22hot_board_page%22%2C%22location%22%3A%22news_hot_card%22%2C%22page_location%22%3A%22hot_board_page%22%2C%22source%22%3A%22trending_tab%22%2C%22style_id%22%3A%2240132%22%2C%22title%22%3A%22%E4%BC%8A%E6%9C%97%EF%BC%9A6%E5%90%8D%E7%BE%8E%E5%9B%BD%E4%B8%AD%E6%83%85%E5%B1%80%E5%AE%98%E5%91%98%E5%9C%A8%E9%98%BF%E8%81%94%E9%85%8B%E8%BA%AB%E4%BA%A1%22%7D&rank=&style_id=40132&topic_id=7612139587531522057"
  }, {
    "title" : "高校跨地区设校区你怎么看",
    "link" : "https://www.toutiao.com/trending/7612232861480321050/?category_name=topic_innerflow&event_type=hot_board&log_pb=%7B%22category_name%22%3A%22topic_innerflow%22%2C%22cluster_type%22%3A%2210%22%2C%22enter_from%22%3A%22click_category%22%2C%22entrance_hotspot%22%3A%22outside%22%2C%22event_type%22%3A%22hot_board%22%2C%22hot_board_cluster_id%22%3A%227612232861480321050%22%2C%22hot_board_impr_id%22%3A%222026030210222522875065DDD0B16A9F23%22%2C%22jump_page%22%3A%22hot_board_page%22%2C%22location%22%3A%22news_hot_card%22%2C%22page_location%22%3A%22hot_board_page%22%2C%22source%22%3A%22trending_tab%22%2C%22style_id%22%3A%2240132%22%2C%22title%22%3A%22%E9%AB%98%E6%A0%A1%E8%B7%A8%E5%9C%B0%E5%8C%BA%E8%AE%BE%E6%A0%A1%E5%8C%BA%E4%BD%A0%E6%80%8E%E4%B9%88%E7%9C%8B%22%7D&rank=&style_id=40132&topic_id=7612232861480321050"
  }, {
    "title" : "NBA常规赛：骑士106-102力克篮网",
    "link" : "https://www.toutiao.com/trending/7612300365598130195/?category_name=topic_innerflow&event_type=hot_board&log_pb=%7B%22category_name%22%3A%22topic_innerflow%22%2C%22cluster_type%22%3A%228%22%2C%22enter_from%22%3A%22click_category%22%2C%22entrance_hotspot%22%3A%22outside%22%2C%22event_type%22%3A%22hot_board%22%2C%22hot_board_cluster_id%22%3A%227612300365598130195%22%2C%22hot_board_impr_id%22%3A%222026030210222522875065DDD0B16A9F23%22%2C%22jump_page%22%3A%22hot_board_page%22%2C%22location%22%3A%22news_hot_card%22%2C%22page_location%22%3A%22hot_board_page%22%2C%22source%22%3A%22trending_tab%22%2C%22style_id%22%3A%2240132%22%2C%22title%22%3A%22NBA%E5%B8%B8%E8%A7%84%E8%B5%9B%EF%BC%9A%E9%AA%91%E5%A3%AB106-102%E5%8A%9B%E5%85%8B%E7%AF%AE%E7%BD%91%22%7D&rank=&style_id=40132&topic_id=7612300365598130195"
  }, {
    "title" : "速览中东危局40小时",
    "link" : "https://www.toutiao.com/trending/7612430984750829097/?category_name=topic_innerflow&event_type=hot_board&log_pb=%7B%22category_name%22%3A%22topic_innerflow%22%2C%22cluster_type%22%3A%225%22%2C%22enter_from%22%3A%22click_category%22%2C%22entrance_hotspot%22%3A%22outside%22%2C%22event_type%22%3A%22hot_board%22%2C%22hot_board_cluster_id%22%3A%227612430984750829097%22%2C%22hot_board_impr_id%22%3A%222026030210222522875065DDD0B16A9F23%22%2C%22jump_page%22%3A%22hot_board_page%22%2C%22location%22%3A%22news_hot_card%22%2C%22page_location%22%3A%22hot_board_page%22%2C%22source%22%3A%22trending_tab%22%2C%22style_id%22%3A%2240132%22%2C%22title%22%3A%22%E9%80%9F%E8%A7%88%E4%B8%AD%E4%B8%9C%E5%8D%B1%E5%B1%8040%E5%B0%8F%E6%97%B6%22%7D&rank=&style_id=40132&topic_id=7612430984750829097"
  }, {
    "title" : "男子首次带女友回家 全家隆重迎接",
    "link" : "https://www.toutiao.com/trending/7612385915591213102/?category_name=topic_innerflow&event_type=hot_board&log_pb=%7B%22category_name%22%3A%22topic_innerflow%22%2C%22cluster_type%22%3A%226%22%2C%22enter_from%22%3A%22click_category%22%2C%22entrance_hotspot%22%3A%22outside%22%2C%22event_type%22%3A%22hot_board%22%2C%22hot_board_cluster_id%22%3A%227612385915591213102%22%2C%22hot_board_impr_id%22%3A%222026030210222522875065DDD0B16A9F23%22%2C%22jump_page%22%3A%22hot_board_page%22%2C%22location%22%3A%22news_hot_card%22%2C%22page_location%22%3A%22hot_board_page%22%2C%22source%22%3A%22trending_tab%22%2C%22style_id%22%3A%2240132%22%2C%22title%22%3A%22%E7%94%B7%E5%AD%90%E9%A6%96%E6%AC%A1%E5%B8%A6%E5%A5%B3%E5%8F%8B%E5%9B%9E%E5%AE%B6+%E5%85%A8%E5%AE%B6%E9%9A%86%E9%87%8D%E8%BF%8E%E6%8E%A5%22%7D&rank=&style_id=40132&topic_id=7612385915591213102"
  } ],
  "BBC中文网热点" : [ {
    "title" : "美國以色列聯手攻擊伊朗，伊朗最高領袖哈梅內伊喪生，伊朗發動報復性空襲——我們目前知道什麼？",
    "link" : "https://www.bbc.com/zhongwen/articles/c87549gz8vwo/trad?at_medium=RSS&at_campaign=rss"
  }, {
    "title" : "分析：押注伊朗政權更迭可能是特朗普迄今最大的豪賭",
    "link" : "https://www.bbc.com/zhongwen/articles/cx2gd3y70xwo/trad?at_medium=RSS&at_campaign=rss"
  }, {
    "title" : "伊朗：哈梅內伊的鐵腕統治結束",
    "link" : "https://www.bbc.com/zhongwen/articles/c1e940735ppo/trad?at_medium=RSS&at_campaign=rss"
  }, {
    "title" : "連結安德魯與愛潑斯坦的第三人曝光",
    "link" : "https://www.bbc.com/zhongwen/articles/cgjzny6z44go/trad?at_medium=RSS&at_campaign=rss"
  }, {
    "title" : "為何美國以色列此刻出手？伊朗進入「生存模式」，結局仍充滿變數",
    "link" : "https://www.bbc.com/zhongwen/articles/cy57glv45lgo/trad?at_medium=RSS&at_campaign=rss"
  }, {
    "title" : "分析：這是一個危險時刻，但美國與以色列認為機不可失",
    "link" : "https://www.bbc.com/zhongwen/articles/c5yg953jd4wo/trad?at_medium=RSS&at_campaign=rss"
  }, {
    "title" : "「夢境工程」讓我們更快樂 —— 還能讓我們買更多啤酒？",
    "link" : "https://www.bbc.com/zhongwen/articles/cn0z9g50rpvo/trad?at_medium=RSS&at_campaign=rss"
  }, {
    "title" : "「人民越來越窮」：伊朗經濟困境如何改變民眾生活",
    "link" : "https://www.bbc.com/zhongwen/articles/cg5n1de4v5yo/trad?at_medium=RSS&at_campaign=rss"
  }, {
    "title" : "二二八79週年掀「台灣史補課潮」，新生代如何與歷史對話？",
    "link" : "https://www.bbc.com/zhongwen/articles/c043gz5gd47o/trad?at_medium=RSS&at_campaign=rss"
  }, {
    "title" : "愛潑斯坦文件：麥克斯韋如何將克林頓帶進了「淫媒」的交際圈",
    "link" : "https://www.bbc.com/zhongwen/articles/cy7jegr7k3jo/trad?at_medium=RSS&at_campaign=rss"
  } ],
  "IT之家日榜" : [ {
    "title" : "人民海军展示航母厕所系统：辽宁舰有几十个不同类型厕所，便池堵塞溢水等相对复杂故障可专线保修",
    "link" : "https://www.ithome.com/0/924/748.htm"
  }, {
    "title" : "宗馥莉砍掉机器人业务，娃哈哈精机公司已解散清算",
    "link" : "https://www.ithome.com/0/924/796.htm"
  }, {
    "title" : "万志强：魅族 23 已完成开发但不会推向市场，后续 Flyme 仍提供基本维护",
    "link" : "https://www.ithome.com/0/924/861.htm"
  }, {
    "title" : "Vision GT 确认不会量产：系小米汽车在硬核科技基础之外的一次深度探索，展车后续将在国内亮相",
    "link" : "https://www.ithome.com/0/924/832.htm"
  }, {
    "title" : "雷军放出小米 Vision Gran Turismo 双门超跑官图，实车明日亮相 MWC 2026",
    "link" : "https://www.ithome.com/0/924/750.htm"
  }, {
    "title" : "徕卡设计师亲自操刀：小米 17 Ultra 徕卡版手机全新「黑银色」首发亮相，承袭 M 系列相机语言",
    "link" : "https://www.ithome.com/0/924/761.htm"
  }, {
    "title" : "更新内容超多：华为鸿蒙 HarmonyOS 6.0.0.328 花粉 Beta 版本亮点抢先看",
    "link" : "https://www.ithome.com/0/924/831.htm"
  }, {
    "title" : "比亚迪推出汉 L、唐 L 限时购车权益：首付 6.98 万元起，提供 7 年低息、3 年 0 息",
    "link" : "https://www.ithome.com/0/924/800.htm"
  }, {
    "title" : "荣耀 Magic V6 首发亮相 MWC 2026：折叠状态 8.75mm 挑战全球最薄，3 月 10 日国行发布",
    "link" : "https://www.ithome.com/0/924/846.htm"
  }, {
    "title" : "2026 年 2 月汽车销量 / 交付榜出炉：上汽集团 269465 辆第一、比亚迪 190190 辆新能源销冠",
    "link" : "https://www.ithome.com/0/924/866.htm"
  } ],
  "懂球帝热门推荐" : [ {
    "title" : "迈阿密4-2逆转奥兰多城，梅西助攻+双响，塞戈维亚传射",
    "link" : "https://www.dongqiudi.com/article/5692374"
  }, {
    "title" : "记者：赛后篮协主席、郭士强和赵睿都哭了，大家压力确实很大",
    "link" : "https://www.dongqiudi.com/article/5691177"
  }, {
    "title" : "Here we go！罗马诺：33岁林加德将加盟科林蒂安",
    "link" : "https://www.dongqiudi.com/article/5690096"
  }, {
    "title" : "剑南春｜米兰2-0客胜克雷莫内塞，帕夫洛维奇、莱奥尾声破门",
    "link" : "https://www.dongqiudi.com/article/5691168"
  }, {
    "title" : "巴萨官方：莱万眼眶骨折，缺席对阵马竞的国王杯比赛",
    "link" : "https://www.dongqiudi.com/article/5691117"
  }, {
    "title" : "剑南春｜阿森纳2-1切尔西，萨利巴、廷贝尔破门，内托染红",
    "link" : "https://www.dongqiudi.com/article/5691830"
  }, {
    "title" : "半场战报：阿森纳1-1切尔西，萨利巴破门，因卡皮耶自摆乌龙",
    "link" : "https://www.dongqiudi.com/article/5691710"
  }, {
    "title" : "剑南春｜富勒姆2-1热刺，威尔逊传射，里沙利松破门难救主",
    "link" : "https://www.dongqiudi.com/article/5691527"
  }, {
    "title" : "剑南春｜曼联2-1逆转水晶宫，B费传射，拉克鲁瓦闪击+染红",
    "link" : "https://www.dongqiudi.com/article/5691534"
  }, {
    "title" : "中国男篮100-93逆转中国台北，朱俊龙19分，胡金秋15+6，陈盈骏26分",
    "link" : "https://www.dongqiudi.com/article/5690719"
  } ]
}