{
  "date" : "2026-07-22",
  "百度热搜" : [ {
    "title" : " 习近平瞩望的“人民城市” ",
    "link" : "https://www.baidu.com/s?wd=%E4%B9%A0%E8%BF%91%E5%B9%B3%E7%9E%A9%E6%9C%9B%E7%9A%84%E2%80%9C%E4%BA%BA%E6%B0%91%E5%9F%8E%E5%B8%82%E2%80%9D&sa=fyb_news&rsv_dl=fyb_news"
  }, {
    "title" : " 巨浪击沉游轮游客漂流5小时 有人吓吐 ",
    "link" : "https://www.baidu.com/s?wd=%E5%B7%A8%E6%B5%AA%E5%87%BB%E6%B2%89%E6%B8%B8%E8%BD%AE%E6%B8%B8%E5%AE%A2%E6%BC%82%E6%B5%815%E5%B0%8F%E6%97%B6+%E6%9C%89%E4%BA%BA%E5%90%93%E5%90%90&sa=fyb_news&rsv_dl=fyb_news"
  }, {
    "title" : " 儿童独自坐高铁攻略刷屏 官方提醒 ",
    "link" : "https://www.baidu.com/s?wd=%E5%84%BF%E7%AB%A5%E7%8B%AC%E8%87%AA%E5%9D%90%E9%AB%98%E9%93%81%E6%94%BB%E7%95%A5%E5%88%B7%E5%B1%8F+%E5%AE%98%E6%96%B9%E6%8F%90%E9%86%92&sa=fyb_news&rsv_dl=fyb_news"
  }, {
    "title" : " 中国科技这3组数字真提气 ",
    "link" : "https://www.baidu.com/s?wd=%E4%B8%AD%E5%9B%BD%E7%A7%91%E6%8A%80%E8%BF%993%E7%BB%84%E6%95%B0%E5%AD%97%E7%9C%9F%E6%8F%90%E6%B0%94&sa=fyb_news&rsv_dl=fyb_news"
  }, {
    "title" : " “中药首富”马兴田夫妇被判赔14亿 ",
    "link" : "https://www.baidu.com/s?wd=%E2%80%9C%E4%B8%AD%E8%8D%AF%E9%A6%96%E5%AF%8C%E2%80%9D%E9%A9%AC%E5%85%B4%E7%94%B0%E5%A4%AB%E5%A6%87%E8%A2%AB%E5%88%A4%E8%B5%9414%E4%BA%BF&sa=fyb_news&rsv_dl=fyb_news"
  }, {
    "title" : " 王祖贤AI人脸授权代言游戏IP ",
    "link" : "https://www.baidu.com/s?wd=%E7%8E%8B%E7%A5%96%E8%B4%A4AI%E4%BA%BA%E8%84%B8%E6%8E%88%E6%9D%83%E4%BB%A3%E8%A8%80%E6%B8%B8%E6%88%8FIP&sa=fyb_news&rsv_dl=fyb_news"
  }, {
    "title" : " 这些充电习惯正悄悄缩短手机寿命 ",
    "link" : "https://www.baidu.com/s?wd=%E8%BF%99%E4%BA%9B%E5%85%85%E7%94%B5%E4%B9%A0%E6%83%AF%E6%AD%A3%E6%82%84%E6%82%84%E7%BC%A9%E7%9F%AD%E6%89%8B%E6%9C%BA%E5%AF%BF%E5%91%BD&sa=fyb_news&rsv_dl=fyb_news"
  }, {
    "title" : " 全国最后一位长征女红军王全英逝世 ",
    "link" : "https://www.baidu.com/s?wd=%E5%85%A8%E5%9B%BD%E6%9C%80%E5%90%8E%E4%B8%80%E4%BD%8D%E9%95%BF%E5%BE%81%E5%A5%B3%E7%BA%A2%E5%86%9B%E7%8E%8B%E5%85%A8%E8%8B%B1%E9%80%9D%E4%B8%96&sa=fyb_news&rsv_dl=fyb_news"
  }, {
    "title" : " 只剩72小时！中国果断出手跨国追索 ",
    "link" : "https://www.baidu.com/s?wd=%E5%8F%AA%E5%89%A972%E5%B0%8F%E6%97%B6%EF%BC%81%E4%B8%AD%E5%9B%BD%E6%9E%9C%E6%96%AD%E5%87%BA%E6%89%8B%E8%B7%A8%E5%9B%BD%E8%BF%BD%E7%B4%A2&sa=fyb_news&rsv_dl=fyb_news"
  }, {
    "title" : " 人工智能专业“杀疯了” 分数普涨 ",
    "link" : "https://www.baidu.com/s?wd=%E4%BA%BA%E5%B7%A5%E6%99%BA%E8%83%BD%E4%B8%93%E4%B8%9A%E2%80%9C%E6%9D%80%E7%96%AF%E4%BA%86%E2%80%9D+%E5%88%86%E6%95%B0%E6%99%AE%E6%B6%A8&sa=fyb_news&rsv_dl=fyb_news"
  } ],
  "新浪微博热搜" : [ {
    "title" : "曝詹姆斯突然改变想法",
    "link" : "https://s.weibo.com/weibo?q=%23%E6%9B%9D%E8%A9%B9%E5%A7%86%E6%96%AF%E7%AA%81%E7%84%B6%E6%94%B9%E5%8F%98%E6%83%B3%E6%B3%95%23"
  }, {
    "title" : "父亲在家长群公开夫妻矛盾被认定家暴",
    "link" : "https://s.weibo.com/weibo?q=%23%E7%88%B6%E4%BA%B2%E5%9C%A8%E5%AE%B6%E9%95%BF%E7%BE%A4%E5%85%AC%E5%BC%80%E5%A4%AB%E5%A6%BB%E7%9F%9B%E7%9B%BE%E8%A2%AB%E8%AE%A4%E5%AE%9A%E5%AE%B6%E6%9A%B4%23"
  }, {
    "title" : "梦想启程且歌且行",
    "link" : "https://s.weibo.com/weibo?q=%23%E6%A2%A6%E6%83%B3%E5%90%AF%E7%A8%8B%E4%B8%94%E6%AD%8C%E4%B8%94%E8%A1%8C%23"
  }, {
    "title" : "九门 提档",
    "link" : "https://s.weibo.com/weibo?q=%E4%B9%9D%E9%97%A8+%E6%8F%90%E6%A1%A3"
  }, {
    "title" : "退钱哥晒世界杯球票账单",
    "link" : "https://s.weibo.com/weibo?q=%23%E9%80%80%E9%92%B1%E5%93%A5%E6%99%92%E4%B8%96%E7%95%8C%E6%9D%AF%E7%90%83%E7%A5%A8%E8%B4%A6%E5%8D%95%23"
  }, {
    "title" : "田曦薇青风吹又生定妆",
    "link" : "https://s.weibo.com/weibo?q=%23%E7%94%B0%E6%9B%A6%E8%96%87%E9%9D%92%E9%A3%8E%E5%90%B9%E5%8F%88%E7%94%9F%E5%AE%9A%E5%A6%86%23"
  }, {
    "title" : "还是以前的老师比较敢写评语",
    "link" : "https://s.weibo.com/weibo?q=%E8%BF%98%E6%98%AF%E4%BB%A5%E5%89%8D%E7%9A%84%E8%80%81%E5%B8%88%E6%AF%94%E8%BE%83%E6%95%A2%E5%86%99%E8%AF%84%E8%AF%AD"
  }, {
    "title" : "朋友圈和微博的差别belike",
    "link" : "https://s.weibo.com/weibo?q=%E6%9C%8B%E5%8F%8B%E5%9C%88%E5%92%8C%E5%BE%AE%E5%8D%9A%E7%9A%84%E5%B7%AE%E5%88%ABbelike"
  }, {
    "title" : "唯一面朝西班牙的阿根廷球员",
    "link" : "https://s.weibo.com/weibo?q=%23%E5%94%AF%E4%B8%80%E9%9D%A2%E6%9C%9D%E8%A5%BF%E7%8F%AD%E7%89%99%E7%9A%84%E9%98%BF%E6%A0%B9%E5%BB%B7%E7%90%83%E5%91%98%23"
  }, {
    "title" : "不要用豆包解决人际关系矛盾",
    "link" : "https://s.weibo.com/weibo?q=%E4%B8%8D%E8%A6%81%E7%94%A8%E8%B1%86%E5%8C%85%E8%A7%A3%E5%86%B3%E4%BA%BA%E9%99%85%E5%85%B3%E7%B3%BB%E7%9F%9B%E7%9B%BE"
  } ],
  "今日头条热榜" : [ {
    "title" : "中央气象台三预警齐发",
    "link" : "https://www.toutiao.com/trending/7664807362415018035/?category_name=topic_innerflow&event_type=hot_board&log_pb=%7B%22category_name%22%3A%22topic_innerflow%22%2C%22cluster_type%22%3A%228%22%2C%22enter_from%22%3A%22click_category%22%2C%22entrance_hotspot%22%3A%22outside%22%2C%22event_type%22%3A%22hot_board%22%2C%22hot_board_cluster_id%22%3A%227664807362415018035%22%2C%22hot_board_impr_id%22%3A%2220260722100121F49C18924A0320DCE534%22%2C%22jump_page%22%3A%22hot_board_page%22%2C%22location%22%3A%22news_hot_card%22%2C%22page_location%22%3A%22hot_board_page%22%2C%22source%22%3A%22trending_tab%22%2C%22style_id%22%3A%2240132%22%2C%22title%22%3A%22%E4%B8%AD%E5%A4%AE%E6%B0%94%E8%B1%A1%E5%8F%B0%E4%B8%89%E9%A2%84%E8%AD%A6%E9%BD%90%E5%8F%91%22%7D&rank=&style_id=40132&topic_id=7664807362415018035"
  }, {
    "title" : "菲律宾为何总精准卡点挑衅",
    "link" : "https://www.toutiao.com/trending/7664963780593323563/?category_name=topic_innerflow&event_type=hot_board&log_pb=%7B%22category_name%22%3A%22topic_innerflow%22%2C%22cluster_type%22%3A%221%22%2C%22enter_from%22%3A%22click_category%22%2C%22entrance_hotspot%22%3A%22outside%22%2C%22event_type%22%3A%22hot_board%22%2C%22hot_board_cluster_id%22%3A%227664963780593323563%22%2C%22hot_board_impr_id%22%3A%2220260722100121F49C18924A0320DCE534%22%2C%22jump_page%22%3A%22hot_board_page%22%2C%22location%22%3A%22news_hot_card%22%2C%22page_location%22%3A%22hot_board_page%22%2C%22source%22%3A%22trending_tab%22%2C%22style_id%22%3A%2240132%22%2C%22title%22%3A%22%E8%8F%B2%E5%BE%8B%E5%AE%BE%E4%B8%BA%E4%BD%95%E6%80%BB%E7%B2%BE%E5%87%86%E5%8D%A1%E7%82%B9%E6%8C%91%E8%A1%85%22%7D&rank=&style_id=40132&topic_id=7664963780593323563"
  }, {
    "title" : "世界人工智能大会达成丰硕成果",
    "link" : "https://www.toutiao.com/article/7664780601328714255"
  }, {
    "title" : "女子临近退休差点多等11年领养老金",
    "link" : "https://www.toutiao.com/trending/7664819309566672906/?category_name=topic_innerflow&event_type=hot_board&log_pb=%7B%22category_name%22%3A%22topic_innerflow%22%2C%22cluster_type%22%3A%226%22%2C%22enter_from%22%3A%22click_category%22%2C%22entrance_hotspot%22%3A%22outside%22%2C%22event_type%22%3A%22hot_board%22%2C%22hot_board_cluster_id%22%3A%227664819309566672906%22%2C%22hot_board_impr_id%22%3A%2220260722100121F49C18924A0320DCE534%22%2C%22jump_page%22%3A%22hot_board_page%22%2C%22location%22%3A%22news_hot_card%22%2C%22page_location%22%3A%22hot_board_page%22%2C%22source%22%3A%22trending_tab%22%2C%22style_id%22%3A%2240132%22%2C%22title%22%3A%22%E5%A5%B3%E5%AD%90%E4%B8%B4%E8%BF%91%E9%80%80%E4%BC%91%E5%B7%AE%E7%82%B9%E5%A4%9A%E7%AD%8911%E5%B9%B4%E9%A2%86%E5%85%BB%E8%80%81%E9%87%91%22%7D&rank=&style_id=40132&topic_id=7664819309566672906"
  }, {
    "title" : "最爱发钱老板透露公司不打卡不考核",
    "link" : "https://www.toutiao.com/trending/7665114866558209546/?category_name=topic_innerflow&event_type=hot_board&log_pb=%7B%22category_name%22%3A%22topic_innerflow%22%2C%22cluster_type%22%3A%222%22%2C%22enter_from%22%3A%22click_category%22%2C%22entrance_hotspot%22%3A%22outside%22%2C%22event_type%22%3A%22hot_board%22%2C%22hot_board_cluster_id%22%3A%227665114866558209546%22%2C%22hot_board_impr_id%22%3A%2220260722100121F49C18924A0320DCE534%22%2C%22jump_page%22%3A%22hot_board_page%22%2C%22location%22%3A%22news_hot_card%22%2C%22page_location%22%3A%22hot_board_page%22%2C%22source%22%3A%22trending_tab%22%2C%22style_id%22%3A%2240132%22%2C%22title%22%3A%22%E6%9C%80%E7%88%B1%E5%8F%91%E9%92%B1%E8%80%81%E6%9D%BF%E9%80%8F%E9%9C%B2%E5%85%AC%E5%8F%B8%E4%B8%8D%E6%89%93%E5%8D%A1%E4%B8%8D%E8%80%83%E6%A0%B8%22%7D&rank=&style_id=40132&topic_id=7665114866558209546"
  }, {
    "title" : "马犬被洪水冲走自行回家瘦成皮包骨",
    "link" : "https://www.toutiao.com/trending/7664779239618789402/?category_name=topic_innerflow&event_type=hot_board&log_pb=%7B%22category_name%22%3A%22topic_innerflow%22%2C%22cluster_type%22%3A%222%22%2C%22enter_from%22%3A%22click_category%22%2C%22entrance_hotspot%22%3A%22outside%22%2C%22event_type%22%3A%22hot_board%22%2C%22hot_board_cluster_id%22%3A%227664779239618789402%22%2C%22hot_board_impr_id%22%3A%2220260722100121F49C18924A0320DCE534%22%2C%22jump_page%22%3A%22hot_board_page%22%2C%22location%22%3A%22news_hot_card%22%2C%22page_location%22%3A%22hot_board_page%22%2C%22source%22%3A%22trending_tab%22%2C%22style_id%22%3A%2240132%22%2C%22title%22%3A%22%E9%A9%AC%E7%8A%AC%E8%A2%AB%E6%B4%AA%E6%B0%B4%E5%86%B2%E8%B5%B0%E8%87%AA%E8%A1%8C%E5%9B%9E%E5%AE%B6%E7%98%A6%E6%88%90%E7%9A%AE%E5%8C%85%E9%AA%A8%22%7D&rank=&style_id=40132&topic_id=7664779239618789402"
  }, {
    "title" : "媒体探访从小树林出圈的“26版西游记”",
    "link" : "https://www.toutiao.com/trending/7664544012321295915/?category_name=topic_innerflow&event_type=hot_board&log_pb=%7B%22category_name%22%3A%22topic_innerflow%22%2C%22cluster_type%22%3A%221%22%2C%22enter_from%22%3A%22click_category%22%2C%22entrance_hotspot%22%3A%22outside%22%2C%22event_type%22%3A%22hot_board%22%2C%22hot_board_cluster_id%22%3A%227664544012321295915%22%2C%22hot_board_impr_id%22%3A%2220260722100121F49C18924A0320DCE534%22%2C%22jump_page%22%3A%22hot_board_page%22%2C%22location%22%3A%22news_hot_card%22%2C%22page_location%22%3A%22hot_board_page%22%2C%22source%22%3A%22trending_tab%22%2C%22style_id%22%3A%2240132%22%2C%22title%22%3A%22%E5%AA%92%E4%BD%93%E6%8E%A2%E8%AE%BF%E4%BB%8E%E5%B0%8F%E6%A0%91%E6%9E%97%E5%87%BA%E5%9C%88%E7%9A%84%E2%80%9C26%E7%89%88%E8%A5%BF%E6%B8%B8%E8%AE%B0%E2%80%9D%22%7D&rank=&style_id=40132&topic_id=7664544012321295915"
  }, {
    "title" : "郑州2死2伤火灾系人为纵火 嫌犯被捕",
    "link" : "https://www.toutiao.com/trending/7665158356633407018/?category_name=topic_innerflow&event_type=hot_board&log_pb=%7B%22category_name%22%3A%22topic_innerflow%22%2C%22cluster_type%22%3A%225%22%2C%22enter_from%22%3A%22click_category%22%2C%22entrance_hotspot%22%3A%22outside%22%2C%22event_type%22%3A%22hot_board%22%2C%22hot_board_cluster_id%22%3A%227665158356633407018%22%2C%22hot_board_impr_id%22%3A%2220260722100121F49C18924A0320DCE534%22%2C%22jump_page%22%3A%22hot_board_page%22%2C%22location%22%3A%22news_hot_card%22%2C%22page_location%22%3A%22hot_board_page%22%2C%22source%22%3A%22trending_tab%22%2C%22style_id%22%3A%2240132%22%2C%22title%22%3A%22%E9%83%91%E5%B7%9E2%E6%AD%BB2%E4%BC%A4%E7%81%AB%E7%81%BE%E7%B3%BB%E4%BA%BA%E4%B8%BA%E7%BA%B5%E7%81%AB+%E5%AB%8C%E7%8A%AF%E8%A2%AB%E6%8D%95%22%7D&rank=&style_id=40132&topic_id=7665158356633407018"
  }, {
    "title" : "英国政府明抢中企钢厂背后",
    "link" : "https://www.toutiao.com/trending/7664970049442024966/?category_name=topic_innerflow&event_type=hot_board&log_pb=%7B%22category_name%22%3A%22topic_innerflow%22%2C%22cluster_type%22%3A%2213%22%2C%22enter_from%22%3A%22click_category%22%2C%22entrance_hotspot%22%3A%22outside%22%2C%22event_type%22%3A%22hot_board%22%2C%22hot_board_cluster_id%22%3A%227664970049442024966%22%2C%22hot_board_impr_id%22%3A%2220260722100121F49C18924A0320DCE534%22%2C%22jump_page%22%3A%22hot_board_page%22%2C%22location%22%3A%22news_hot_card%22%2C%22page_location%22%3A%22hot_board_page%22%2C%22source%22%3A%22trending_tab%22%2C%22style_id%22%3A%2240132%22%2C%22title%22%3A%22%E8%8B%B1%E5%9B%BD%E6%94%BF%E5%BA%9C%E6%98%8E%E6%8A%A2%E4%B8%AD%E4%BC%81%E9%92%A2%E5%8E%82%E8%83%8C%E5%90%8E%22%7D&rank=&style_id=40132&topic_id=7664970049442024966"
  }, {
    "title" : "专访河南漂流哥",
    "link" : "https://www.toutiao.com/trending/7664577125198069787/?category_name=topic_innerflow&event_type=hot_board&log_pb=%7B%22category_name%22%3A%22topic_innerflow%22%2C%22cluster_type%22%3A%221%22%2C%22enter_from%22%3A%22click_category%22%2C%22entrance_hotspot%22%3A%22outside%22%2C%22event_type%22%3A%22hot_board%22%2C%22hot_board_cluster_id%22%3A%227664577125198069787%22%2C%22hot_board_impr_id%22%3A%2220260722100121F49C18924A0320DCE534%22%2C%22jump_page%22%3A%22hot_board_page%22%2C%22location%22%3A%22news_hot_card%22%2C%22page_location%22%3A%22hot_board_page%22%2C%22source%22%3A%22trending_tab%22%2C%22style_id%22%3A%2240132%22%2C%22title%22%3A%22%E4%B8%93%E8%AE%BF%E6%B2%B3%E5%8D%97%E6%BC%82%E6%B5%81%E5%93%A5%22%7D&rank=&style_id=40132&topic_id=7664577125198069787"
  } ],
  "BBC中文网热点" : [ {
    "title" : "「如果有一座橋」：翔安機場啟用在即，金門人怎麼看北京的「情感工程」？",
    "link" : "https://www.bbc.com/zhongwen/articles/cx25g733w65o/trad?at_medium=RSS&at_campaign=rss"
  }, {
    "title" : "APEC前夕四個月，中國深圳地鐵突加強安檢惹民怨",
    "link" : "https://www.bbc.com/zhongwen/articles/c9q97x49gd4o/trad?at_medium=RSS&at_campaign=rss"
  }, {
    "title" : "貝安德的隨性風格能否經受唐寧街10號的考驗？",
    "link" : "https://www.bbc.com/zhongwen/articles/cdewkr7e307o/trad?at_medium=RSS&at_campaign=rss"
  }, {
    "title" : "台灣防空演習將首度模擬「斷網」，象徵防衛思維轉型？",
    "link" : "https://www.bbc.com/zhongwen/articles/cn5n4krydr7o/trad?at_medium=RSS&at_campaign=rss"
  }, {
    "title" : "貝克漢為何成為世界盃在美國的門面人物",
    "link" : "https://www.bbc.com/zhongwen/articles/cly8vlyr1mzo/trad?at_medium=RSS&at_campaign=rss"
  }, {
    "title" : "托雷斯加時建功助西班牙險勝阿根廷 二奪世界盃冠軍",
    "link" : "https://www.bbc.com/zhongwen/articles/crk547p26rpo/trad?at_medium=RSS&at_campaign=rss"
  }, {
    "title" : "更多比賽，更多爭議——該如何評價2026年FIFA世界盃？",
    "link" : "https://www.bbc.com/zhongwen/articles/clyxj2pky5go/trad?at_medium=RSS&at_campaign=rss"
  }, {
    "title" : "梅西、馬拉多納、貝利——誰才是真正的足球史上最強？",
    "link" : "https://www.bbc.com/zhongwen/articles/c9w0jqyqngdo/trad?at_medium=RSS&at_campaign=rss"
  }, {
    "title" : "2026足球世界盃賽程海報  點擊這裡免費下載",
    "link" : "https://www.bbc.com/zhongwen/articles/cx21r3d9y1yo/trad?at_medium=RSS&at_campaign=rss"
  }, {
    "title" : "兩岸之間只剩三公里：金門對面多了一座巨型機場，台灣憂軍事與飛航安全",
    "link" : "https://www.bbc.com/zhongwen/articles/c3v0x30ny39o/trad?at_medium=RSS&at_campaign=rss"
  } ],
  "IT之家日榜" : [ {
    "title" : "消息称小米手机今年出货目标由 9000 万部上调至 1.1 亿部，内部认为存储行情有望反转",
    "link" : "https://www.ithome.com/0/979/328.htm"
  }, {
    "title" : "高德地图“位置口令”上线：说不清位置不用怕，发送 6 个数字即可",
    "link" : "https://www.ithome.com/0/979/448.htm"
  }, {
    "title" : "消息称苹果打样 7 英寸超大屏，有概率用于 iPhone 20 Pro Max",
    "link" : "https://www.ithome.com/0/979/386.htm"
  }, {
    "title" : "苹果 iPhone 18 Pro / Max 爆料汇总：A20 芯片、可变光圈等",
    "link" : "https://www.ithome.com/0/979/589.htm"
  }, {
    "title" : "吉利银河 TT Ultra 开启预售：20.98 万元，首发限量 999 台",
    "link" : "https://www.ithome.com/0/979/772.htm"
  }, {
    "title" : "华为鸿蒙 HarmonyOS 6.1.0.135 版本“隐藏”特性曝光：默认图标优化、耳机控制页面布局调整",
    "link" : "https://www.ithome.com/0/979/804.htm"
  }, {
    "title" : "央视曝乙游年龄门槛形同虚设，13 岁女孩为游戏狂刷 3 万元",
    "link" : "https://www.ithome.com/0/979/460.htm"
  }, {
    "title" : "雷军：小米澎程系列车型 WLTC 亏电油耗最低至 5.7L/100km，长途出行偶尔用油也很省",
    "link" : "https://www.ithome.com/0/979/626.htm"
  }, {
    "title" : "全球首款机器人手机：荣耀 Robot Phone 拍照页面曝光，将支持大师电影模式",
    "link" : "https://www.ithome.com/0/979/801.htm"
  }, {
    "title" : "realme 按下中国市场暂停键，真我副总裁徐起发布告别视频",
    "link" : "https://www.ithome.com/0/979/710.htm"
  } ],
  "懂球帝热门推荐" : [ {
    "title" : "反复横跳，C罗取消了对“FIFA保送梅西”切片的点赞",
    "link" : "https://www.dongqiudi.com/article/6065077"
  }, {
    "title" : "莫雷托：皇马接近与罗德里达成合同协议，但还没和曼城谈判",
    "link" : "https://www.dongqiudi.com/article/6064805"
  }, {
    "title" : "FIFA官方世界杯最佳阵容候选：西班牙6人、阿根廷5人在列",
    "link" : "https://www.dongqiudi.com/article/6063450"
  }, {
    "title" : "官方：切尔西签下维拉中场摩根-罗杰斯；据悉转会费1.17亿镑",
    "link" : "https://www.dongqiudi.com/article/6064637"
  }, {
    "title" : "美媒评世界杯最令人失望阵容：C罗、诺伊尔上榜",
    "link" : "https://www.dongqiudi.com/article/6063238"
  }, {
    "title" : "英格兰名哨安东尼-泰勒宣布退休：现在是时候退到一边了",
    "link" : "https://www.dongqiudi.com/article/6063596"
  }, {
    "title" : "DO：利雅得新月即将签下荷兰国脚萨默维尔，转会费约8000万欧",
    "link" : "https://www.dongqiudi.com/article/6063788"
  }, {
    "title" : "申花4-1逆转海牛晋级足协杯8强，阿苏埃帽子戏法+助攻+伤退",
    "link" : "https://www.dongqiudi.com/article/6063143"
  }, {
    "title" : "英超名哨安东尼-泰勒宣布退休，裁判生涯共执法432英超",
    "link" : "https://www.dongqiudi.com/article/6063613"
  }, {
    "title" : "总比分河南6-7英博，斯坦丘破门，马拉尼昂、阿卜杜肉苏力失点",
    "link" : "https://www.dongqiudi.com/article/6063552"
  } ]
}